LICENSE
MANIFEST.in
README.md
setup.cfg
setup.py
docs/About.rst
docs/Changelog.rst
src/senaite/__init__.py
src/senaite.app.listing.egg-info/PKG-INFO
src/senaite.app.listing.egg-info/SOURCES.txt
src/senaite.app.listing.egg-info/dependency_links.txt
src/senaite.app.listing.egg-info/entry_points.txt
src/senaite.app.listing.egg-info/namespace_packages.txt
src/senaite.app.listing.egg-info/not-zip-safe
src/senaite.app.listing.egg-info/requires.txt
src/senaite.app.listing.egg-info/top_level.txt
src/senaite/app/__init__.py
src/senaite/app/listing/__init__.py
src/senaite/app/listing/ajax.py
src/senaite/app/listing/configure.zcml
src/senaite/app/listing/controlpanel.py
src/senaite/app/listing/decorators.py
src/senaite/app/listing/interfaces.py
src/senaite/app/listing/setuphandlers.py
src/senaite/app/listing/utils.py
src/senaite/app/listing/view.py
src/senaite/app/listing/adapters/__init__.py
src/senaite/app/listing/adapters/childfolderitems.py
src/senaite/app/listing/adapters/configure.zcml
src/senaite/app/listing/adapters/transitions.py
src/senaite/app/listing/adapters/workflow.py
src/senaite/app/listing/browser/__init__.py
src/senaite/app/listing/browser/configure.zcml
src/senaite/app/listing/browser/static/resources.pt
src/senaite/app/listing/browser/static/bundles/senaite.app.listing.eb760ee.css
src/senaite/app/listing/browser/static/bundles/senaite.app.listing.eb760ee.js
src/senaite/app/listing/browser/static/bundles/senaite.app.listing.eb760ee.js.LICENSE.txt
src/senaite/app/listing/browser/viewlets/__init__.py
src/senaite/app/listing/browser/viewlets/configure.zcml
src/senaite/app/listing/browser/viewlets/resources.py
src/senaite/app/listing/profiles/default/metadata.xml
src/senaite/app/listing/profiles/default/registry.xml
src/senaite/app/listing/profiles/default/senaite.app.listing.txt
src/senaite/app/listing/profiles/uninstall/metadata.xml
src/senaite/app/listing/profiles/uninstall/registry.xml
src/senaite/app/listing/profiles/uninstall/senaite.app.listing.uninstall.txt
src/senaite/app/listing/templates/contents_table.pt
src/senaite/app/listing/templates/contents_table_view.pt
src/senaite/app/listing/templates/listing.pt
src/senaite/app/listing/upgrades/__init__.py
src/senaite/app/listing/upgrades/configure.zcml
src/senaite/app/listing/upgrades/handlers.py