Metadata-Version: 2.1
Name: senaite.app.listing
Version: 2.6.0
Summary: ReactJS powered listing tables for SENAITE LIMS
Home-page: https://github.com/senaite/senaite.app.listing
Author: RIDING BYTES & NARALABS
Author-email: senaite@senaite.com
License: GPLv2
Keywords: senaite,lims,opensource,reactjs
Platform: UNKNOWN
Classifier: Programming Language :: Python
Classifier: Framework :: Plone
Classifier: Framework :: Zope2
Provides-Extra: test
